LICENSE
README.md
setup.py
evalgen/__init__.py
evalgen/cli.py
evalgen/lib.py
evalgen.egg-info/PKG-INFO
evalgen.egg-info/SOURCES.txt
evalgen.egg-info/dependency_links.txt
evalgen.egg-info/entry_points.txt
evalgen.egg-info/requires.txt
evalgen.egg-info/top_level.txt
evalgen/access/__init__.py
evalgen/llm/__init__.py
evalgen/specification/__init__.py